ruskit/__init__.py
ruskit/cli.py
ruskit/cluster.py
ruskit/utils.py
ruskit/cmds/__init__.py
ruskit/cmds/add.py
ruskit/cmds/create.py
ruskit/cmds/manage.py
ruskit-0.0.7.dist-info/DESCRIPTION.rst
ruskit-0.0.7.dist-info/entry_points.txt
ruskit-0.0.7.dist-info/METADATA
ruskit-0.0.7.dist-info/metadata.json
ruskit-0.0.7.dist-info/RECORD
ruskit-0.0.7.dist-info/top_level.txt
ruskit-0.0.7.dist-info/WHEEL
