Metadata-Version: 2.0
Name: ruskit
Version: 0.0.7
Summary: Redis cluster administration toolkit
Home-page: https://github.com/eleme/ruskit
Author: maralla
Author-email: imaralla@icloud.com
License: MIT
Platform: UNKNOWN
Classifier: Development Status :: 3 - Alpha
Classifier: Intended Audience :: Developers
Classifier: Topic :: Software Development
Classifier: License :: OSI Approved :: MIT License
Classifier: Programming Language :: Python :: 2.7
Classifier: Programming Language :: Python :: 3.3
Classifier: Programming Language :: Python :: 3.4
Requires-Dist: hiredis
Requires-Dist: redis
